distilltower/__init__.py
distilltower/distilltower.py
distilltower-0.0.1.dist-info/LICENSE
distilltower-0.0.1.dist-info/METADATA
distilltower-0.0.1.dist-info/WHEEL
distilltower-0.0.1.dist-info/top_level.txt
distilltower-0.0.1.dist-info/RECORD
