Metadata-Version: 2.1
Name: distilltower
Version: 0.0.1
Summary: Modeling the relationship between production parameters and quality of distillation tower, and grading the importance of parameters
Author: Jiang Wanlong
Project-URL: Homepage, https://github.com/pypa/sampleproject
Project-URL: Bug Tracker, https://github.com/pypa/sampleproject/issues
Classifier: Programming Language :: Python :: 3
Classifier: License :: OSI Approved :: MIT License
Classifier: Operating System :: OS Independent
Requires-Python: >=3.5
License-File: LICENSE
